7_segment.v
module gray_to_7seg (
  input [2:0] gray,
  output reg [6:0] seg // {a,b,c,d,e,f,g}
);

  always @(*) begin
    case (gray)
      3'b000: seg = 7'b1111110; // 0
      3'b001: seg = 7'b0110000; // 1
      3'b011: seg = 7'b1101101; // 2
      3'b010: seg = 7'b1111001; // 3
      3'b110: seg = 7'b0110011; // 4
      3'b111: seg = 7'b1011011; // 5
      3'b101: seg = 7'b1011111; // 6
      3'b100: seg = 7'b1110000; // 7
      default: seg = 7'b0000000; // blank
    endcase
  end
endmodule

assignment3/7_segment_tb.v
module tb_gray_to_7seg;
  reg [2:0] gray;
  wire [6:0] seg;

  gray_to_7seg uut (.gray(gray), .seg(seg));

  initial begin
    $dumpfile("gray7seg.vcd");
    $dumpvars(0, tb_gray_to_7seg);

    gray = 3'b000; #10;
    gray = 3'b001; #10;
    gray = 3'b011; #10;
    gray = 3'b010; #10;
    gray = 3'b110; #10;
    gray = 3'b111; #10;
    gray = 3'b101; #10;
    gray = 3'b100; #10;

    $finish;
  end
endmodule

gray7seg.vcd
$date
	Sat May 30 14:34:55 2026
$end
$version
	Icarus Verilog
$end
$timescale
	1s
$end
$scope module tb_gray_to_7seg $end
$var wire 7 ! seg [6:0] $end
$var reg 3 " gray [2:0] $end
$scope module uut $end
$var wire 3 # gray [2:0] $end
$var reg 7 $ seg [6:0] $end
$upscope $end
$upscope $end
$enddefinitions $end
#0
$dumpvars
b1111110 $
b0 #
b0 "
b1111110 !
$end
#10
b110000 !
b110000 $
b1 "
b1 #
#20
b1101101 !
b1101101 $
b11 "
b11 #
#30
b1111001 !
b1111001 $
b10 "
b10 #
#40
b110011 !
b110011 $
b110 "
b110 #
#50
b1011011 !
b1011011 $
b111 "
b111 #
#60
b1011111 !
b1011111 $
b101 "
b101 #
#70
b1110000 !
b1110000 $
b100 "
b100 #
